bmwwAPI/__init__.py
bmwwAPI/bwAPI.py
bmwwAPI/users.py
bmwwAPI/work.py
bmww_api-0.0.9.dist-info/METADATA
bmww_api-0.0.9.dist-info/WHEEL
bmww_api-0.0.9.dist-info/top_level.txt
bmww_api-0.0.9.dist-info/RECORD
